MolToGraph/MolToGraph.py
MolToGraph/__init__.py
models/GNNModel.py
models/GraphGNNModel.py
models/GraphLevelGNN.py
models/__init__.py
MolGNN_update-0.0.2.dist-info/LICENSE
MolGNN_update-0.0.2.dist-info/METADATA
MolGNN_update-0.0.2.dist-info/WHEEL
MolGNN_update-0.0.2.dist-info/top_level.txt
MolGNN_update-0.0.2.dist-info/RECORD
