Metadata-Version: 2.1
Name: MolGNN-update
Version: 0.0.2
Summary: UNKNOWN
Home-page: UNKNOWN
Author: Giulio Mattedi
Author-email: lxu110@stu.suda.edu.cn
License: MIT License
Platform: UNKNOWN
Requires-Python: >=3.5, <=3.8
License-File: LICENSE
Requires-Dist: rdkit
Requires-Dist: torch
Requires-Dist: numpy
Requires-Dist: torch-geometric
Requires-Dist: torch-scatter
Requires-Dist: torch-sparse
